air_vapour_pressure_dynamics/__init__.py
air_vapour_pressure_dynamics/base/__init__.py
air_vapour_pressure_dynamics/calculations/__init__.py
air_vapour_pressure_dynamics/core/__init__.py
air_vapour_pressure_dynamics/extra/__init__.py
air_vapour_pressure_dynamics/extra/_float.py
air_vapour_pressure_dynamics/extra/_numpy.py
air_vapour_pressure_dynamics/extra/_sympy.py
air_vapour_pressure_dynamics/initialize/__init__.py
air_vapour_pressure_dynamics-1.8.10.data/data/requirements.txt
air_vapour_pressure_dynamics-1.8.10.data/data/.git/config
air_vapour_pressure_dynamics-1.8.10.dist-info/LICENSE
air_vapour_pressure_dynamics-1.8.10.dist-info/METADATA
air_vapour_pressure_dynamics-1.8.10.dist-info/WHEEL
air_vapour_pressure_dynamics-1.8.10.dist-info/top_level.txt
air_vapour_pressure_dynamics-1.8.10.dist-info/RECORD
