Metadata-Version: 2.1
Name: air_vapour_pressure_dynamics
Version: 1.8.10
Summary: air_vapour_pressure_dynamics: 
Home-page: https://github.com/R-Rijnbeek/air_vapour_pressure_dynamics
Author: Robert Rijnbeek
Author-email: robert270384@gmail.com
Project-URL: Bug Tracker, https://github.com/R-Rijnbeek/air_vapour_pressure_dynamics/issues
Classifier: Programming Language :: Python :: 3
Classifier: License :: OSI Approved :: MIT License
Classifier: Operating System :: OS Independent
Requires-Python: >=3.10
License-File: LICENSE
Requires-Dist: basic-decorators
